<?xml version="1.0" encoding="UTF-8"?><record_update table="sp_widget">
    <sp_widget action="INSERT_OR_UPDATE">
        <category>custom</category>
        <client_script><![CDATA[api.controller=function() {
  /* widget controller */
  var c = this;
};
]]></client_script>
        <controller_as>c</controller_as>
        <css/>
        <data_table>sp_instance</data_table>
        <demo_data/>
        <description/>
        <docs/>
        <field_list/>
        <has_preview>true</has_preview>
        <id>first_application</id>
        <internal>false</internal>
        <link><![CDATA[function link(scope, element, attrs, controller) {  }]]></link>
        <name>First application</name>
        <option_schema/>
        <public>false</public>
        <roles/>
        <script><![CDATA[(function() {
  /* populate the 'data' object */
  /* e.g., data.table = $sp.getValue('table'); */

	/* La tabella di riferimento su ServiceNow contenente i nominativ, è la seguente:
	 * x_58872_needit_nominativi
	 */
	
})();]]></script>
        <servicenow>false</servicenow>
        <sys_class_name>sp_widget</sys_class_name>
        <sys_created_by>admin</sys_created_by>
        <sys_created_on>2021-02-08 11:41:07</sys_created_on>
        <sys_id>a5942a002f522010142856f62799b69f</sys_id>
        <sys_mod_count>19</sys_mod_count>
        <sys_name>First application</sys_name>
        <sys_package display_value="NeedIt" source="x_58872_needit">6ead8e780f603200cd674f8ce1050ed1</sys_package>
        <sys_policy/>
        <sys_scope display_value="NeedIt">6ead8e780f603200cd674f8ce1050ed1</sys_scope>
        <sys_update_name>sp_widget_a5942a002f522010142856f62799b69f</sys_update_name>
        <sys_updated_by>admin</sys_updated_by>
        <sys_updated_on>2021-02-08 11:56:03</sys_updated_on>
        <template><![CDATA[<div class="row">
  <div class="col-sm-12">
 <button type="button" class="btn btn-primary" data-toggle="modal" data-target="#exampleModal3">
  Aggiungi nominativo
</button>
</div>
  </div>

<div class="row">
  <div class="col-sm-12">
  <table id="example" class="table table-striped table-bordered" style="width:100%">
    <thead>
      <tr>
        <th>Nome</th>
        <th>Cognome</th>
        <th>Email</th>
        <th>Azione</th>
      </tr>
    </thead>
    <tbody>
      <!--struttura da rendere dinamica-->
      <tr>
        <td>Gaetano</td>
        <td>De Mitri</td>
        <td>gaetano.demitri@itpas.it</td>
        <td>
          <button type="button" class="btn btn-warning" data-toggle="modal" data-target="#exampleModal">
  Modifica
</button>
        <button type="button" class="btn btn-danger" data-toggle="modal" data-target="#exampleModal2">
  Elimina
</button></td>
      </tr>
    </tbody>
  </table>
  </div>
</div>

<!-- Modal Elimina -->
<div class="modal fade" id="exampleModal2" tabindex="-1" role="dialog" aria-labelledby="exampleModalLabel" aria-hidden="true">
  <div class="modal-dialog" role="document">
    <div class="modal-content">
      <div class="modal-header">
        <h5 class="modal-title" id="exampleModalLabel"><b>Conferma nominativo</b></h5>
        <button type="button" class="close" data-dismiss="modal" aria-label="Close">
          <span aria-hidden="true">&times;</span>
        </button>
      </div>
      <div class="modal-body">
        Confermi la cancellazione del nominativo?
      </div>
      <div class="modal-footer">
        <button type="button" class="btn btn-secondary" data-dismiss="modal">Close</button>
        <button type="button" class="btn btn-primary">Conferma</button>
      </div>
    </div>
  </div>
</div>


<!-- Modal Modifica -->
<div class="modal fade" id="exampleModal" tabindex="-1" role="dialog" aria-labelledby="exampleModalLabel" aria-hidden="true">
  <div class="modal-dialog" role="document">
    <div class="modal-content">
      <div class="modal-header">
        <h5 class="modal-title" id="exampleModalLabel"><b>Modifica nominativo</b></h5>
        <button type="button" class="close" data-dismiss="modal" aria-label="Close">
          <span aria-hidden="true">&times;</span>
        </button>
      </div>
      <div class="modal-body">
        ...
      </div>
      <div class="modal-footer">
        <button type="button" class="btn btn-secondary" data-dismiss="modal">Close</button>
        <button type="button" class="btn btn-primary">Aggiungi</button>
      </div>
    </div>
  </div>
</div>

<!-- Modal Aggiungi -->
<div class="modal fade" id="exampleModal3" tabindex="-1" role="dialog" aria-labelledby="exampleModalLabel" aria-hidden="true">
  <div class="modal-dialog" role="document">
    <div class="modal-content">
      <div class="modal-header">
        <h5 class="modal-title" id="exampleModalLabel"><b>Aggiungi nominativo</b></h5>
        <button type="button" class="close" data-dismiss="modal" aria-label="Close">
          <span aria-hidden="true">&times;</span>
        </button>
      </div>
      <div class="modal-body">
        ...
      </div>
      <div class="modal-footer">
        <button type="button" class="btn btn-secondary" data-dismiss="modal">Close</button>
        <button type="button" class="btn btn-primary">Aggiungi</button>
      </div>
    </div>
  </div>
</div>]]></template>
    </sp_widget>
</record_update>
